deflator/__init__.py
deflator/api_call.py
deflator/deflator.py
deflator/utils.py
deflatepybr-0.0.8.dist-info/METADATA
deflatepybr-0.0.8.dist-info/WHEEL
deflatepybr-0.0.8.dist-info/top_level.txt
deflatepybr-0.0.8.dist-info/RECORD
